botocote/__init__.py
botocote/operations.py
botocote-0.0.1.dist-info/LICENSE
botocote-0.0.1.dist-info/METADATA
botocote-0.0.1.dist-info/WHEEL
botocote-0.0.1.dist-info/top_level.txt
botocote-0.0.1.dist-info/RECORD
