Metadata-Version: 2.1
Name: botocote
Version: 0.0.1
Summary: A small example package trying to typosquat botocore
Author-email: Ranjeet Ramalingam <rranjeet@gmail.com>
Project-URL: Homepage, https://github.com/rranjeet/botocote
Project-URL: Bug Tracker, https://github.com/rranjeet/botocote/issues
Classifier: Programming Language :: Python :: 3
Classifier: License :: OSI Approved :: MIT License
Classifier: Operating System :: OS Independent
Requires-Python: >=3.7
License-File: LICENSE
